{
  "artifact": "single_variable_experiment_results",
  "generated_at": "2026-04-23T14:35:30.684101+00:00",
  "experiment_scope": "single_variable_only_absolute_momentum_floor_on_return_20d",
  "single_variable_name": "absolute_momentum_floor_on_return_20d",
  "baseline_reference": "output/walk_forward_with_costs_summary.json",
  "tested_variants": [
    0.0,
    0.01,
    0.02,
    0.03
  ],
  "results_by_variant": [
    {
      "threshold_value": 0.0,
      "in_sample_avg_return_per_trade": 0.3134,
      "oos_avg_return_per_trade": -0.3909,
      "holdout_avg_return_per_trade": -0.7867,
      "oos_max_drawdown_pct": 37.5149,
      "holdout_max_drawdown_pct": 34.6411,
      "trade_count": 461,
      "passes_minimum_criteria": false,
      "assessment_note": "Fails at least one locked minimum criterion; no escape clause or range expansion allowed.",
      "baseline_comparison": {
        "oos_avg_return_per_trade_before": -0.3909,
        "oos_avg_return_per_trade_after": -0.3909,
        "holdout_avg_return_per_trade_before": -0.7867,
        "holdout_avg_return_per_trade_after": -0.7867,
        "oos_max_drawdown_pct_before": 37.5149,
        "oos_max_drawdown_pct_after": 37.5149,
        "holdout_max_drawdown_pct_before": 34.6411,
        "holdout_max_drawdown_pct_after": 34.6411,
        "trade_count_before": 461,
        "trade_count_after": 461
      }
    },
    {
      "threshold_value": 0.01,
      "in_sample_avg_return_per_trade": 0.3669,
      "oos_avg_return_per_trade": -0.3046,
      "holdout_avg_return_per_trade": -0.7552,
      "oos_max_drawdown_pct": 34.9949,
      "holdout_max_drawdown_pct": 35.1012,
      "trade_count": 449,
      "passes_minimum_criteria": false,
      "assessment_note": "Fails at least one locked minimum criterion; no escape clause or range expansion allowed.",
      "baseline_comparison": {
        "oos_avg_return_per_trade_before": -0.3909,
        "oos_avg_return_per_trade_after": -0.3046,
        "holdout_avg_return_per_trade_before": -0.7867,
        "holdout_avg_return_per_trade_after": -0.7552,
        "oos_max_drawdown_pct_before": 37.5149,
        "oos_max_drawdown_pct_after": 34.9949,
        "holdout_max_drawdown_pct_before": 34.6411,
        "holdout_max_drawdown_pct_after": 35.1012,
        "trade_count_before": 461,
        "trade_count_after": 449
      }
    },
    {
      "threshold_value": 0.02,
      "in_sample_avg_return_per_trade": 0.4596,
      "oos_avg_return_per_trade": -0.2184,
      "holdout_avg_return_per_trade": -0.7931,
      "oos_max_drawdown_pct": 33.5006,
      "holdout_max_drawdown_pct": 33.9511,
      "trade_count": 423,
      "passes_minimum_criteria": false,
      "assessment_note": "Fails at least one locked minimum criterion; no escape clause or range expansion allowed.",
      "baseline_comparison": {
        "oos_avg_return_per_trade_before": -0.3909,
        "oos_avg_return_per_trade_after": -0.2184,
        "holdout_avg_return_per_trade_before": -0.7867,
        "holdout_avg_return_per_trade_after": -0.7931,
        "oos_max_drawdown_pct_before": 37.5149,
        "oos_max_drawdown_pct_after": 33.5006,
        "holdout_max_drawdown_pct_before": 34.6411,
        "holdout_max_drawdown_pct_after": 33.9511,
        "trade_count_before": 461,
        "trade_count_after": 423
      }
    },
    {
      "threshold_value": 0.03,
      "in_sample_avg_return_per_trade": 0.5888,
      "oos_avg_return_per_trade": -0.0659,
      "holdout_avg_return_per_trade": -0.744,
      "oos_max_drawdown_pct": 27.0655,
      "holdout_max_drawdown_pct": 33.9554,
      "trade_count": 399,
      "passes_minimum_criteria": false,
      "assessment_note": "Fails at least one locked minimum criterion; no escape clause or range expansion allowed.",
      "baseline_comparison": {
        "oos_avg_return_per_trade_before": -0.3909,
        "oos_avg_return_per_trade_after": -0.0659,
        "holdout_avg_return_per_trade_before": -0.7867,
        "holdout_avg_return_per_trade_after": -0.744,
        "oos_max_drawdown_pct_before": 37.5149,
        "oos_max_drawdown_pct_after": 27.0655,
        "holdout_max_drawdown_pct_before": 34.6411,
        "holdout_max_drawdown_pct_after": 33.9554,
        "trade_count_before": 461,
        "trade_count_after": 399
      }
    }
  ],
  "minimum_pass_criteria": {
    "metric_basis": "same walk-forward evaluation with the same realism-cost policy already documented",
    "oos_avg_return_per_trade_gt": 0.0,
    "oos_max_drawdown_pct_lt": 35.0,
    "holdout_avg_return_per_trade_floor": -0.1,
    "trade_count_floor": 350,
    "no_worse_than_current_holdout": true
  },
  "winner_variant": null,
  "winner_selection_basis": "no_variant_passed_locked_minimum_criteria",
  "hypothesis_result": "hypothesis_rejected",
  "hypothesis_result_reason": "None of the four approved threshold values passed the locked minimum criteria, so the hypothesis is rejected without expanding the range, loosening pass criteria, or adding a second variable.",
  "no_range_expansion_performed": true,
  "stack_changed": false,
  "retest_status": "blocked",
  "paper_trading_status": "blocked",
  "next_action": "review_single_variable_experiment_result_against_locked_criteria_before_any_further_strategy_change"
}